ipchecker/__init__.py
ipchecker/__main__.py
ipchecker/conf.py
ipchecker/ipchecker.py
ip_checker-1.2.2.dist-info/LICENSE
ip_checker-1.2.2.dist-info/METADATA
ip_checker-1.2.2.dist-info/WHEEL
ip_checker-1.2.2.dist-info/entry_points.txt
ip_checker-1.2.2.dist-info/top_level.txt
ip_checker-1.2.2.dist-info/RECORD
