Metadata-Version: 2.1
Name: ip-checker
Version: 1.2.2
Summary: Scan connected IP's using GreyNoise API
Home-page: https://github.com/mickgl/ip-checker
Author: michgl
Author-email: <michgl33s@gmail.com>
License: MIT License
Platform: UNKNOWN
Classifier: Development Status :: 1 - Planning
Classifier: Intended Audience :: Developers
Classifier: License :: OSI Approved :: MIT License
Classifier: Programming Language :: Python :: 3
Classifier: Operating System :: POSIX
